wisenations/__init__.py
wisenations/decors.py
wisenations/exceptions.py
wisenations/finals.py
wisenations/main.py
wisenations/utils.py
wisenations-0.0.0.dev0.dist-info/METADATA
wisenations-0.0.0.dev0.dist-info/WHEEL
wisenations-0.0.0.dev0.dist-info/top_level.txt
wisenations-0.0.0.dev0.dist-info/RECORD
