Metadata-Version: 2.4
Name: wisenations
Version: 0.0.0.dev0
Summary: A simple library for NationStates RP stats management and evaluation
Author-email: Orly Neto <orly2carvalhoneto@gmail.com>
Maintainer-email: Orly Neto <orly2carvalhoneto@gmail.com>
License-Expression: MIT
Project-URL: Repository, https://github.com/Stalot/WiseNations
Project-URL: Issues, https://github.com/Stalot/WiseNations/issues
Project-URL: Changelog, https://github.com/Stalot/WiseNations/blob/main/CHANGELOG.md
Keywords: NationStates,Roleplay
Classifier: Development Status :: 2 - Pre-Alpha
Classifier: Intended Audience :: Developers
Classifier: Programming Language :: Python
Classifier: Operating System :: OS Independent
Requires-Python: >=3.10
